postman_to_pytest/__init__.py
postman_to_pytest/postman_to_pytest.py
postman_to_pytest-1.0.0.dist-info/licenses/LICENSE
postman_to_pytest-1.0.0.dist-info/METADATA
postman_to_pytest-1.0.0.dist-info/WHEEL
postman_to_pytest-1.0.0.dist-info/entry_points.txt
postman_to_pytest-1.0.0.dist-info/top_level.txt
postman_to_pytest-1.0.0.dist-info/RECORD
