Metadata-Version: 2.4
Name: postman-to-pytest
Version: 1.0.0
Summary: A tool to convert Postman collections to pytest test files
Home-page: https://github.com/benz1k1/postman-to-pytest
Author: Barun Yadav
Author-email: Barun Yadav <benz3k3@gmail.com>
License: MIT License
Project-URL: Homepage, https://github.com/benz1k1/postman-to-pytest
Project-URL: Repository, https://github.com/benz1k1/postman-to-pytest.git
Project-URL: Bug Tracker, https://github.com/benz1k1/postman-to-pytest/issues
Keywords: postman,pytest,testing,api,converter
Classifier: Development Status :: 5 - Production/Stable
Classifier: Intended Audience :: Developers
Classifier: Topic :: Software Development :: Testing
Classifier: Programming Language :: Python :: 3
Classifier: Programming Language :: Python :: 3.8
Classifier: Programming Language :: Python :: 3.9
Classifier: Programming Language :: Python :: 3.10
Classifier: Programming Language :: Python :: 3.11
Classifier: Programming Language :: Python :: 3.12
Classifier: License :: OSI Approved :: MIT License
Classifier: Operating System :: OS Independent
Requires-Python: >=3.8
License-File: LICENSE
Provides-Extra: dev
Requires-Dist: pytest>=7.4.0; extra == "dev"
Requires-Dist: pytest-cov>=4.1.0; extra == "dev"
Requires-Dist: black>=22.3.0; extra == "dev"
Requires-Dist: isort>=5.10.1; extra == "dev"
Requires-Dist: flake8>=4.0.1; extra == "dev"
Requires-Dist: twine>=4.0.2; extra == "dev"
Requires-Dist: build>=0.10.0; extra == "dev"
Dynamic: author
Dynamic: home-page
Dynamic: license-file
Dynamic: requires-python
